tinysdk/__init__.py
tinysdk/database.py
tinysdk/messaging.py
tinysdk/storage.py
tinysdk/utils/__init__.py
tinysdk/utils/decorators.py
tinysdk/utils/helpers.py
tinysdk-0.1.0.dist-info/licenses/LICENSE
tinysdk-0.1.0.dist-info/METADATA
tinysdk-0.1.0.dist-info/WHEEL
tinysdk-0.1.0.dist-info/top_level.txt
tinysdk-0.1.0.dist-info/RECORD
