Metadata-Version: 2.4
Name: tinysdk
Version: 0.1.0
Summary: Shared services for TinyAI microservices platform
Author: Synapze GmbH
Maintainer: Synapze GmbH
License: MIT
Project-URL: Homepage, https://github.com/SynapzeGmbH/TinySDK
Project-URL: Repository, https://github.com/SynapzeGmbH/TinySDK
Project-URL: Issues, https://github.com/SynapzeGmbH/TinySDK/issues
Keywords: microservices,mongodb,minio,rabbitmq,tinyai
Classifier: Development Status :: 3 - Alpha
Classifier: Intended Audience :: Developers
Classifier: License :: OSI Approved :: MIT License
Classifier: Programming Language :: Python :: 3
Classifier: Programming Language :: Python :: 3.8
Classifier: Programming Language :: Python :: 3.9
Classifier: Programming Language :: Python :: 3.10
Classifier: Programming Language :: Python :: 3.11
Classifier: Programming Language :: Python :: 3.12
Classifier: Topic :: Software Development :: Libraries :: Python Modules
Requires-Python: >=3.8
License-File: LICENSE
Requires-Dist: pymongo>=4.6.3
Requires-Dist: pika>=1.3.0
Requires-Dist: minio>=7.0.0
Requires-Dist: urllib3
Requires-Dist: certifi
Provides-Extra: dev
Requires-Dist: pytest>=7.0.0; extra == "dev"
Requires-Dist: pytest-cov>=4.0.0; extra == "dev"
Requires-Dist: ruff>=0.1.0; extra == "dev"
Requires-Dist: build>=1.0.0; extra == "dev"
Requires-Dist: twine>=4.0.0; extra == "dev"
Dynamic: license-file
